watttime/__init__.py
watttime/api.py
watttime/tcy.py
watttime-1.3.2.dist-info/METADATA
watttime-1.3.2.dist-info/WHEEL
watttime-1.3.2.dist-info/top_level.txt
watttime-1.3.2.dist-info/RECORD
