Metadata-Version: 2.2
Name: watttime
Version: 1.3.2
Summary: An officially maintained python client for WattTime's API providing access to electricity grid emissions data.
Requires-Python: >=3.8
Requires-Dist: requests
Requires-Dist: pandas>1.0.0
Requires-Dist: holidays
Requires-Dist: python-dateutil
Dynamic: description
Dynamic: description-content-type
Dynamic: requires-dist
Dynamic: requires-python
Dynamic: summary
